wildRandomPackage/__init__.py
wildRandomPackage/add.py
wildRandomPackage/power.py
wildRandomPackage/subtract.py
wildRandomPackage/extras/__init__.py
wildRandomPackage/extras/divide.py
wildRandomPackage/extras/multiply.py
wildRandomPackage-0.0.3.dist-info/METADATA
wildRandomPackage-0.0.3.dist-info/WHEEL
wildRandomPackage-0.0.3.dist-info/top_level.txt
wildRandomPackage-0.0.3.dist-info/RECORD
